CONTRIBUTORS
LICENSE
MANIFEST.in
README.rst
setup.cfg
setup.py
Tinkerer.egg-info/PKG-INFO
Tinkerer.egg-info/SOURCES.txt
Tinkerer.egg-info/dependency_links.txt
Tinkerer.egg-info/entry_points.txt
Tinkerer.egg-info/requires.txt
Tinkerer.egg-info/top_level.txt
tinkerer/__init__.py
tinkerer/cmdline.py
tinkerer/draft.py
tinkerer/master.py
tinkerer/output.py
tinkerer/page.py
tinkerer/paths.py
tinkerer/post.py
tinkerer/utils.py
tinkerer/writer.py
tinkerer/__templates/conf.py
tinkerer/__templates/index.html
tinkerer/__templates/master.rst
tinkerer/__templates/page.rst
tinkerer/__templates/post.rst
tinkerer/ext/__init__.py
tinkerer/ext/aggregator.py
tinkerer/ext/author.py
tinkerer/ext/blog.py
tinkerer/ext/disqus.py
tinkerer/ext/filing.py
tinkerer/ext/html5.py
tinkerer/ext/metadata.py
tinkerer/ext/patch.py
tinkerer/ext/readmore.py
tinkerer/ext/rss.py
tinkerer/ext/uistr.py
tinkerer/ext/locale/ca/LC_MESSAGES/tinkerer.mo
tinkerer/ext/locale/de/LC_MESSAGES/tinkerer.mo
tinkerer/ext/locale/en_GB/LC_MESSAGES/tinkerer.mo
tinkerer/ext/locale/es/LC_MESSAGES/tinkerer.mo
tinkerer/ext/locale/fr/LC_MESSAGES/tinkerer.mo
tinkerer/ext/locale/it/LC_MESSAGES/tinkerer.mo
tinkerer/ext/locale/ja/LC_MESSAGES/tinkerer.mo
tinkerer/ext/locale/pl/LC_MESSAGES/tinkerer.mo
tinkerer/ext/locale/pt_BR/LC_MESSAGES/tinkerer.mo
tinkerer/ext/locale/ru/LC_MESSAGES/tinkerer.mo
tinkerer/ext/locale/zh_CN/LC_MESSAGES/tinkerer.mo
tinkerer/ext/locale/zh_TW/LC_MESSAGES/tinkerer.mo
tinkerer/static/disqus.js
tinkerer/static/tinkerer.ico
tinkerer/themes/boilerplate/404.html
tinkerer/themes/boilerplate/CHANGELOG.md
tinkerer/themes/boilerplate/CONTRIBUTING.md
tinkerer/themes/boilerplate/LICENSE.md
tinkerer/themes/boilerplate/README.md
tinkerer/themes/boilerplate/aggregated.html
tinkerer/themes/boilerplate/archive.html
tinkerer/themes/boilerplate/categories.html
tinkerer/themes/boilerplate/crossdomain.xml
tinkerer/themes/boilerplate/favicon.ico
tinkerer/themes/boilerplate/humans.txt
tinkerer/themes/boilerplate/layout.html
tinkerer/themes/boilerplate/page.html
tinkerer/themes/boilerplate/recent.html
tinkerer/themes/boilerplate/robots.txt
tinkerer/themes/boilerplate/rss.html
tinkerer/themes/boilerplate/search.html
