Metadata-Version: 1.1
Name: Tinkerer
Version: 1.4.1
Summary: Sphinx-based blogging engine
Home-page: http://tinkerer.me/
Author: Vlad Riscutia
Author-email: riscutiavlad@gmail.com
License: FreeBSD
Download-URL: http://pypi.python.org/pypi/Tinkerer
Platform: any
Classifier: Development Status :: 5 - Production/Stable
Classifier: Environment :: Console
Classifier: Environment :: Web Environment
Classifier: Intended Audience :: End Users/Desktop
Classifier: License :: OSI Approved :: BSD License
Classifier: Operating System :: OS Independent
Classifier: Programming Language :: Python
Classifier: Topic :: Communications
Classifier: Topic :: Internet
